{"nodes": [{"id": "d_desktop_hostel_management_system_backend_controllers_otpcontroller_js", "label": "otpController.js", "file_type": "code", "source_file": "D:\\Desktop\\Hostel-Management-System\\backend\\controllers\\otpController.js", "source_location": "L1"}, {"id": "otpcontroller_gettransporter", "label": "getTransporter()", "file_type": "code", "source_file": "D:\\Desktop\\Hostel-Management-System\\backend\\controllers\\otpController.js", "source_location": "L19"}, {"id": "otpcontroller_generateotp", "label": "generateOTP()", "file_type": "code", "source_file": "D:\\Desktop\\Hostel-Management-System\\backend\\controllers\\otpController.js", "source_location": "L75"}, {"id": "otpcontroller_extractprn", "label": "extractPRN()", "file_type": "code", "source_file": "D:\\Desktop\\Hostel-Management-System\\backend\\controllers\\otpController.js", "source_location": "L76"}], "edges": [{"source": "d_desktop_hostel_management_system_backend_controllers_otpcontroller_js", "target": "otpcontroller_gettransporter", "relation": "contains", "confidence": "EXTRACTED", "source_file": "D:\\Desktop\\Hostel-Management-System\\backend\\controllers\\otpController.js", "source_location": "L19", "weight": 1.0}, {"source": "d_desktop_hostel_management_system_backend_controllers_otpcontroller_js", "target": "otpcontroller_generateotp", "relation": "contains", "confidence": "EXTRACTED", "source_file": "D:\\Desktop\\Hostel-Management-System\\backend\\controllers\\otpController.js", "source_location": "L75", "weight": 1.0}, {"source": "d_desktop_hostel_management_system_backend_controllers_otpcontroller_js", "target": "otpcontroller_extractprn", "relation": "contains", "confidence": "EXTRACTED", "source_file": "D:\\Desktop\\Hostel-Management-System\\backend\\controllers\\otpController.js", "source_location": "L76", "weight": 1.0}], "raw_calls": [{"caller_nid": "otpcontroller_gettransporter", "callee": "createTransport", "source_file": "D:\\Desktop\\Hostel-Management-System\\backend\\controllers\\otpController.js", "source_location": "L27"}, {"caller_nid": "otpcontroller_gettransporter", "callee": "verify", "source_file": "D:\\Desktop\\Hostel-Management-System\\backend\\controllers\\otpController.js", "source_location": "L35"}, {"caller_nid": "otpcontroller_gettransporter", "callee": "log", "source_file": "D:\\Desktop\\Hostel-Management-System\\backend\\controllers\\otpController.js", "source_location": "L36"}, {"caller_nid": "otpcontroller_gettransporter", "callee": "error", "source_file": "D:\\Desktop\\Hostel-Management-System\\backend\\controllers\\otpController.js", "source_location": "L41"}, {"caller_nid": "otpcontroller_gettransporter", "callee": "error", "source_file": "D:\\Desktop\\Hostel-Management-System\\backend\\controllers\\otpController.js", "source_location": "L42"}, {"caller_nid": "otpcontroller_gettransporter", "callee": "error", "source_file": "D:\\Desktop\\Hostel-Management-System\\backend\\controllers\\otpController.js", "source_location": "L43"}, {"caller_nid": "otpcontroller_gettransporter", "callee": "error", "source_file": "D:\\Desktop\\Hostel-Management-System\\backend\\controllers\\otpController.js", "source_location": "L44"}, {"caller_nid": "otpcontroller_gettransporter", "callee": "padEnd", "source_file": "D:\\Desktop\\Hostel-Management-System\\backend\\controllers\\otpController.js", "source_location": "L44"}, {"caller_nid": "otpcontroller_gettransporter", "callee": "slice", "source_file": "D:\\Desktop\\Hostel-Management-System\\backend\\controllers\\otpController.js", "source_location": "L44"}, {"caller_nid": "otpcontroller_gettransporter", "callee": "error", "source_file": "D:\\Desktop\\Hostel-Management-System\\backend\\controllers\\otpController.js", "source_location": "L45"}, {"caller_nid": "otpcontroller_gettransporter", "callee": "error", "source_file": "D:\\Desktop\\Hostel-Management-System\\backend\\controllers\\otpController.js", "source_location": "L46"}, {"caller_nid": "otpcontroller_gettransporter", "callee": "error", "source_file": "D:\\Desktop\\Hostel-Management-System\\backend\\controllers\\otpController.js", "source_location": "L47"}, {"caller_nid": "otpcontroller_gettransporter", "callee": "padEnd", "source_file": "D:\\Desktop\\Hostel-Management-System\\backend\\controllers\\otpController.js", "source_location": "L47"}, {"caller_nid": "otpcontroller_gettransporter", "callee": "error", "source_file": "D:\\Desktop\\Hostel-Management-System\\backend\\controllers\\otpController.js", "source_location": "L48"}, {"caller_nid": "otpcontroller_gettransporter", "callee": "error", "source_file": "D:\\Desktop\\Hostel-Management-System\\backend\\controllers\\otpController.js", "source_location": "L49"}, {"caller_nid": "otpcontroller_gettransporter", "callee": "error", "source_file": "D:\\Desktop\\Hostel-Management-System\\backend\\controllers\\otpController.js", "source_location": "L50"}, {"caller_nid": "otpcontroller_gettransporter", "callee": "error", "source_file": "D:\\Desktop\\Hostel-Management-System\\backend\\controllers\\otpController.js", "source_location": "L51"}, {"caller_nid": "otpcontroller_gettransporter", "callee": "error", "source_file": "D:\\Desktop\\Hostel-Management-System\\backend\\controllers\\otpController.js", "source_location": "L52"}, {"caller_nid": "otpcontroller_gettransporter", "callee": "error", "source_file": "D:\\Desktop\\Hostel-Management-System\\backend\\controllers\\otpController.js", "source_location": "L53"}, {"caller_nid": "otpcontroller_gettransporter", "callee": "error", "source_file": "D:\\Desktop\\Hostel-Management-System\\backend\\controllers\\otpController.js", "source_location": "L54"}, {"caller_nid": "otpcontroller_gettransporter", "callee": "warn", "source_file": "D:\\Desktop\\Hostel-Management-System\\backend\\controllers\\otpController.js", "source_location": "L57"}, {"caller_nid": "otpcontroller_gettransporter", "callee": "createTestAccount", "source_file": "D:\\Desktop\\Hostel-Management-System\\backend\\controllers\\otpController.js", "source_location": "L61"}, {"caller_nid": "otpcontroller_gettransporter", "callee": "createTransport", "source_file": "D:\\Desktop\\Hostel-Management-System\\backend\\controllers\\otpController.js", "source_location": "L62"}, {"caller_nid": "otpcontroller_gettransporter", "callee": "log", "source_file": "D:\\Desktop\\Hostel-Management-System\\backend\\controllers\\otpController.js", "source_location": "L69"}, {"caller_nid": "otpcontroller_generateotp", "callee": "toString", "source_file": "D:\\Desktop\\Hostel-Management-System\\backend\\controllers\\otpController.js", "source_location": "L75"}, {"caller_nid": "otpcontroller_generateotp", "callee": "floor", "source_file": "D:\\Desktop\\Hostel-Management-System\\backend\\controllers\\otpController.js", "source_location": "L75"}, {"caller_nid": "otpcontroller_generateotp", "callee": "random", "source_file": "D:\\Desktop\\Hostel-Management-System\\backend\\controllers\\otpController.js", "source_location": "L75"}, {"caller_nid": "otpcontroller_extractprn", "callee": "split", "source_file": "D:\\Desktop\\Hostel-Management-System\\backend\\controllers\\otpController.js", "source_location": "L76"}, {"caller_nid": "otpcontroller_extractprn", "callee": "toLowerCase", "source_file": "D:\\Desktop\\Hostel-Management-System\\backend\\controllers\\otpController.js", "source_location": "L76"}]}